django_viewcomponent/__init__.py
django_viewcomponent/app_settings.py
django_viewcomponent/apps.py
django_viewcomponent/component.py
django_viewcomponent/component_registry.py
django_viewcomponent/fields.py
django_viewcomponent/loaders.py
django_viewcomponent/preview.py
django_viewcomponent/templates/django_viewcomponent/base.html
django_viewcomponent/templates/django_viewcomponent/index.html
django_viewcomponent/templates/django_viewcomponent/preview.html
django_viewcomponent/templates/django_viewcomponent/previews.html
django_viewcomponent/templatetags/__init__.py
django_viewcomponent/templatetags/viewcomponent_tags.py
django_viewcomponent/urls.py
django_viewcomponent/views.py
django_viewcomponent-1.0.11.dist-info/METADATA
django_viewcomponent-1.0.11.dist-info/WHEEL
django_viewcomponent-1.0.11.dist-info/RECORD
