Metadata-Version: 2.3
Name: django-viewcomponent
Version: 1.0.11
Summary: Build reusable components in Django, inspired by Rails ViewComponent
Home-page: https://github.com/rails-inspire-django/django-viewcomponent
License: MIT
Author: Michael Yin
Author-email: michaelyin@accordbox.com
Requires-Python: >=3.8
Classifier: License :: OSI Approved :: MIT License
Classifier: Programming Language :: Python :: 3
Classifier: Programming Language :: Python :: 3.8
Classifier: Programming Language :: Python :: 3.9
Classifier: Programming Language :: Python :: 3.10
Classifier: Programming Language :: Python :: 3.11
Classifier: Programming Language :: Python :: 3.12
Classifier: Programming Language :: Python :: 3.13
Requires-Dist: django (>=3.0)
Project-URL: Changelog, https://github.com/rails-inspire-django/django-viewcomponent/releases
